setup.cfg
setup.py
bin/codebom
codebom/__init__.py
codebom/_version.py
codebom/_version_test.py
codebom/analyze.py
codebom/analyze_test.py
codebom/bom.py
codebom/bom_test.py
codebom/graph.py
codebom/graph_test.py
codebom/licenseconflict.py
codebom/licenseconflict_test.py
codebom/licenseidentifier.py
codebom/licenseidentifier_test.py
codebom/licenses.py
codebom/lint.py
codebom/lint_test.py
codebom/parseargs.py
codebom/parseargs_test.py
codebom/scan.py
codebom/scan_test.py
codebom/verify.py
codebom/verify_test.py
codebom.egg-info/PKG-INFO
codebom.egg-info/SOURCES.txt
codebom.egg-info/dependency_links.txt
codebom.egg-info/requires.txt
codebom.egg-info/top_level.txt
codebom/licenses/0BSD.txt
codebom/licenses/AAL.txt
codebom/licenses/ADSL.txt
codebom/licenses/AFL-1.1.txt
codebom/licenses/AFL-1.2.txt
codebom/licenses/AFL-2.0.txt
codebom/licenses/AFL-2.1.txt
codebom/licenses/AFL-3.0.txt
codebom/licenses/AGPL-1.0.txt
codebom/licenses/AGPL-3.0.txt
codebom/licenses/AMDPLPA.txt
codebom/licenses/AML.txt
codebom/licenses/AMPAS.txt
codebom/licenses/ANTLR-PD.txt
codebom/licenses/APAFML.txt
codebom/licenses/APL-1.0.txt
codebom/licenses/APSL-1.0.txt
codebom/licenses/APSL-1.1.txt
codebom/licenses/APSL-1.2.txt
codebom/licenses/APSL-2.0.txt
codebom/licenses/Abstyles.txt
codebom/licenses/Adobe-2006.txt
codebom/licenses/Adobe-Glyph.txt
codebom/licenses/Afmparse.txt
codebom/licenses/Aladdin.txt
codebom/licenses/Apache-1.0.txt
codebom/licenses/Apache-1.1.txt
codebom/licenses/Apache-2.0.txt
codebom/licenses/Artistic-1.0-Perl.txt
codebom/licenses/Artistic-1.0-cl8.txt
codebom/licenses/Artistic-1.0.txt
codebom/licenses/Artistic-2.0.txt
codebom/licenses/BSD-2-Clause-FreeBSD.txt
codebom/licenses/BSD-2-Clause-NetBSD.txt
codebom/licenses/BSD-2-Clause.txt
codebom/licenses/BSD-3-Clause-Attribution.txt
codebom/licenses/BSD-3-Clause-Clear.txt
codebom/licenses/BSD-3-Clause-LBNL.txt
codebom/licenses/BSD-3-Clause-No-Nuclear-License-2014.txt
codebom/licenses/BSD-3-Clause-No-Nuclear-License.txt
codebom/licenses/BSD-3-Clause-No-Nuclear-Warranty.txt
codebom/licenses/BSD-3-Clause.txt
codebom/licenses/BSD-4-Clause-UC.txt
codebom/licenses/BSD-4-Clause.txt
