Metadata-Version: 1.0
Name: codebom
Version: 1.0.1
Summary: Command-line tool to create, validate and analyze a Bill of Materials
Home-page: https://github.com/codebom/codebom
Author: Greg Fitzgerald
Author-email: garious@gmail.com
License: UNKNOWN
Platform: UNKNOWN
